code_fmt_tools/__init__.py
code_fmt_tools-0.0.5.dist-info/LICENSE
code_fmt_tools-0.0.5.dist-info/METADATA
code_fmt_tools-0.0.5.dist-info/WHEEL
code_fmt_tools-0.0.5.dist-info/top_level.txt
code_fmt_tools-0.0.5.dist-info/RECORD
