Metadata-Version: 2.1
Name: code_fmt_tools
Version: 0.0.5
Summary: code parser tools
Project-URL: Homepage, https://github.com/ecustwm
License-File: LICENSE
